[{"grass":["https://example.org/colour-with-hierarchy/green"],"gras":["https://example.org/colour-with-hierarchy/green"],"gra":["https://example.org/colour-with-hierarchy/green"],"gr":["https://example.org/colour-with-hierarchy/green"],"g":["https://example.org/colour-with-hierarchy/green"],"rass":["https://example.org/colour-with-hierarchy/green"],"ras":["https://example.org/colour-with-hierarchy/green"],"ra":["https://example.org/colour-with-hierarchy/green"],"r":["https://example.org/colour-with-hierarchy/green"],"ass":["https://example.org/colour-with-hierarchy/green"],"as":["https://example.org/colour-with-hierarchy/green"],"a":["https://example.org/colour-with-hierarchy/green"],"ss":["https://example.org/colour-with-hierarchy/green"],"s":["https://example.org/colour-with-hierarchy/green"]},{"farbig":["https://example.org/colour-with-hierarchy/green"],"farbi":["https://example.org/colour-with-hierarchy/green"],"farb":["https://example.org/colour-with-hierarchy/green"],"far":["https://example.org/colour-with-hierarchy/green"],"fa":["https://example.org/colour-with-hierarchy/green"],"f":["https://example.org/colour-with-hierarchy/green"]},{"arbig":["https://example.org/colour-with-hierarchy/green"],"arbi":["https://example.org/colour-with-hierarchy/green"],"arb":["https://example.org/colour-with-hierarchy/green"],"ar":["https://example.org/colour-with-hierarchy/green"]},{"rbig":["https://example.org/colour-with-hierarchy/green"],"rbi":["https://example.org/colour-with-hierarchy/green"],"rb":["https://example.org/colour-with-hierarchy/green"]},{"big":["https://example.org/colour-with-hierarchy/green"],"bi":["https://example.org/colour-with-hierarchy/green"],"b":["https://example.org/colour-with-hierarchy/green"]},{"ig":["https://example.org/colour-with-hierarchy/green"],"i":["https://example.org/colour-with-hierarchy/green"]},{},{},{}]